dotmvw/__init__.py
dotmvw/dotmvw.py
dotmvw-0.1.4.dist-info/LICENSE
dotmvw-0.1.4.dist-info/METADATA
dotmvw-0.1.4.dist-info/WHEEL
dotmvw-0.1.4.dist-info/top_level.txt
dotmvw-0.1.4.dist-info/RECORD
