Metadata-Version: 2.1
Name: dotmvw
Version: 0.1.4
Summary: For automating the complete HyperView session generation process.
Home-page: https://github.com/yaonuma/dotmvw
Author: Yumitomo Onuma
Author-email: yaonuma@umich.edu
License: UNKNOWN
Platform: UNKNOWN
Classifier: Programming Language :: Python :: 2.7
Classifier: License :: OSI Approved :: Apache Software License
Classifier: Operating System :: OS Independent
Requires-Dist: anytree (>=2.7.3)
